visible_residues/_inner_loop.cpython-312-x86_64-linux-musl.so
visible_residues/api.py
visible_residues/_inner_loop.cc
visible_residues/__init__.py
visible_residues/vendored/eigen/Eigen/SuperLUSupport
visible_residues/vendored/eigen/Eigen/Eigenvalues
visible_residues/vendored/eigen/Eigen/StdDeque
visible_residues/vendored/eigen/Eigen/Dense
visible_residues/vendored/eigen/Eigen/QtAlignedMalloc
visible_residues/vendored/eigen/Eigen/IterativeLinearSolvers
visible_residues/vendored/eigen/Eigen/PaStiXSupport
visible_residues/vendored/eigen/Eigen/MetisSupport
visible_residues/vendored/eigen/Eigen/CholmodSupport
visible_residues/vendored/eigen/Eigen/SparseCore
visible_residues/vendored/eigen/Eigen/Geometry
visible_residues/vendored/eigen/Eigen/Cholesky
visible_residues/vendored/eigen/Eigen/Sparse
visible_residues/vendored/eigen/Eigen/SPQRSupport
visible_residues/vendored/eigen/Eigen/SparseCholesky
visible_residues/vendored/eigen/Eigen/KLUSupport
visible_residues/vendored/eigen/Eigen/OrderingMethods
visible_residues/vendored/eigen/Eigen/Core
visible_residues/vendored/eigen/Eigen/SVD
visible_residues/vendored/eigen/Eigen/QR
visible_residues/vendored/eigen/Eigen/UmfPackSupport
visible_residues/vendored/eigen/Eigen/PardisoSupport
visible_residues/vendored/eigen/Eigen/LU
visible_residues/vendored/eigen/Eigen/Eigen
visible_residues/vendored/eigen/Eigen/Householder
visible_residues/vendored/eigen/Eigen/StdList
visible_residues/vendored/eigen/Eigen/StdVector
visible_residues/vendored/eigen/Eigen/SparseLU
visible_residues/vendored/eigen/Eigen/SparseQR
visible_residues/vendored/eigen/Eigen/Jacobi
visible_residues/vendored/eigen/Eigen/src/StlSupport/StdDeque.h
visible_residues/vendored/eigen/Eigen/src/StlSupport/details.h
visible_residues/vendored/eigen/Eigen/src/StlSupport/StdVector.h
visible_residues/vendored/eigen/Eigen/src/StlSupport/StdList.h
visible_residues/vendored/eigen/Eigen/src/SuperLUSupport/SuperLUSupport.h
visible_residues-0.3.0.dist-info/top_level.txt
visible_residues-0.3.0.dist-info/METADATA
visible_residues-0.3.0.dist-info/RECORD
visible_residues-0.3.0.dist-info/WHEEL
visible_residues-0.3.0.dist-info/licenses/LICENSE.txt
