Metadata-Version: 2.4
Name: visible_residues
Version: 0.3.0
Summary: Find residues with sidechains in a specific region
Author-email: Kale Kundert <kale@thekunderts.net>
Project-URL: Documentation, https://visible-residues.readthedocs.io/en/latest/
Project-URL: Version Control, https://github.com/kalekundert/visible_residues
Project-URL: Bug Tracker, https://github.com/kalekundert/visible_residues/issues
Project-URL: Continuous Integration, https://github.com/kalekundert/visible_residues/actions
Project-URL: Test Coverage, https://app.codecov.io/github/kalekundert/visible_residues
Classifier: Programming Language :: Python :: 3.10
Requires-Python: ~=3.10
License-File: LICENSE.txt
Requires-Dist: numpy
Requires-Dist: polars
Requires-Dist: macromol_dataframe
Provides-Extra: test
Requires-Dist: pytest; extra == "test"
Requires-Dist: parametrize_from_file; extra == "test"
Provides-Extra: doc
Requires-Dist: sphinx; extra == "doc"
Requires-Dist: sphinx_rtd_theme; extra == "doc"
Requires-Dist: myst_parser; extra == "doc"
Requires-Dist: autoclasstoc; extra == "doc"
Dynamic: license-file
